recohut/__init__.py
recohut/_nbdev.py
recohut/core.py
recohut/datasets/__init__.py
recohut/datasets/aotm.py
recohut/datasets/avazu.py
recohut/datasets/base.py
recohut/datasets/criteo.py
recohut/datasets/diginetica.py
recohut/datasets/gowalla.py
recohut/datasets/lastfm.py
recohut/datasets/movielens.py
recohut/datasets/music30.py
recohut/datasets/nowplaying.py
recohut/datasets/retailrocket.py
recohut/datasets/sample_session.py
recohut/datasets/session.py
recohut/datasets/synthetic.py
recohut/datasets/tianchi.py
recohut/datasets/tmall.py
recohut/datasets/weeplaces.py
recohut/datasets/yoochoose.py
recohut/datasets/bases/__init__.py
recohut/datasets/bases/common.py
recohut/datasets/bases/interactions.py
recohut/evaluation/__init__.py
recohut/evaluation/metrics.py
recohut/models/__init__.py
recohut/models/actor_critic.py
recohut/models/afm.py
recohut/models/afn.py
recohut/models/all.py
recohut/models/ar.py
recohut/models/autoint.py
recohut/models/bandits.py
recohut/models/bcq.py
recohut/models/bert.py
recohut/models/cotrec.py
recohut/models/dcn.py
recohut/models/deepfm.py
recohut/models/dnn.py
recohut/models/dssm.py
recohut/models/embedding.py
recohut/models/epsilon.py
recohut/models/factorization.py
recohut/models/ffm.py
recohut/models/fm.py
recohut/models/fnfm.py
recohut/models/fnn.py
recohut/models/gmf.py
recohut/models/groupim.py
recohut/models/hofm.py
recohut/models/lr.py
recohut/models/mf.py
recohut/models/mlp.py
recohut/models/mpm.py
recohut/models/narm.py
recohut/models/ncf.py
recohut/models/nfm.py
recohut/models/nmf.py
recohut/models/pnn.py
recohut/models/prod2vec.py
recohut/models/sasrec.py
recohut/models/siren.py
recohut/models/spop.py
recohut/models/sr.py
recohut/models/srgnn.py
recohut/models/tagnn.py
recohut/models/tagnn_pp.py
recohut/models/ultragcn.py
recohut/models/vsknn.py
recohut/models/wide_and_deep.py
recohut/models/xdeepfm.py
recohut/models/bases/__init__.py
recohut/models/bases/common.py
recohut/models/layers/__init__.py
recohut-0.0.11.dist-info/LICENSE
recohut-0.0.11.dist-info/METADATA
recohut-0.0.11.dist-info/WHEEL
recohut-0.0.11.dist-info/entry_points.txt
recohut-0.0.11.dist-info/top_level.txt
recohut-0.0.11.dist-info/RECORD
