Metadata-Version: 2.1
Name: recohut
Version: 0.0.11
Summary: A python library for building recommender systems.
Home-page: https://github.com/RecoHut-Projects/recohut/tree/master/
Author: recohut
Author-email: recohut@gmail.com
License: Apache Software License 2.0
Keywords: recsys,python,deeplearning,machinelearning
Platform: UNKNOWN
Classifier: Development Status :: 3 - Alpha
Classifier: Intended Audience :: Developers
Classifier: Natural Language :: English
Classifier: Programming Language :: Python :: 3.6
Classifier: Programming Language :: Python :: 3.7
Classifier: Programming Language :: Python :: 3.8
Classifier: License :: OSI Approved :: Apache Software License
Requires-Python: >=3.6
License-File: LICENSE
Requires-Dist: pip
Requires-Dist: packaging
Provides-Extra: dev
